LICENSE
MANIFEST.in
README.rst
setup.py
django_ptvsd/__init__.py
django_ptvsd.egg-info/PKG-INFO
django_ptvsd.egg-info/SOURCES.txt
django_ptvsd.egg-info/dependency_links.txt
django_ptvsd.egg-info/requires.txt
django_ptvsd.egg-info/top_level.txt
django_ptvsd/management/__init__.py
django_ptvsd/management/commands/__init__.py
django_ptvsd/management/commands/runserver.py