Metadata-Version: 1.0
Name: django-ptvsd
Version: 0.0.1
Summary: A Wrapper to Visual Studio remote debugging server for python
Home-page: https://github.com/sthima/django-ptvsd
Author: Daniel Beckert
Author-email: daniel@sthima.com
License: MIT
Platform: UNKNOWN
